boardsonfire_client/__init__.py
boardsonfire_client/client.py
boardsonfire_client/endpoints.py
boardsonfire_client/exceptions.py
boardsonfire_sdk-0.0.1.dist-info/LICENSE
boardsonfire_sdk-0.0.1.dist-info/METADATA
boardsonfire_sdk-0.0.1.dist-info/WHEEL
boardsonfire_sdk-0.0.1.dist-info/top_level.txt
boardsonfire_sdk-0.0.1.dist-info/RECORD
