Metadata-Version: 2.1
Name: boardsonfire-sdk
Version: 0.0.1
Summary: Python SDK for BoardsOnFire API
Project-URL: Homepage, https://github.com/HampB/boardsonfire-sdk-python
Classifier: Programming Language :: Python :: 3
Classifier: License :: OSI Approved :: MIT License
Classifier: Operating System :: OS Independent
Requires-Python: >=3.9
License-File: LICENSE
Requires-Dist: requests
